firebase_idtoken.py
setup.py
firebase_idtoken.egg-info/PKG-INFO
firebase_idtoken.egg-info/SOURCES.txt
firebase_idtoken.egg-info/dependency_links.txt
firebase_idtoken.egg-info/top_level.txt